SimpleEgg/__init__.py
SimpleEgg/spark_session.py
SimpleEgg-0.1.dist-info/METADATA
SimpleEgg-0.1.dist-info/WHEEL
SimpleEgg-0.1.dist-info/top_level.txt
SimpleEgg-0.1.dist-info/RECORD
