Metadata-Version: 2.1
Name: SimpleEgg
Version: 0.1
Summary: Simple example calling Spark from a custom package
Home-page: https://github.com/curtishoward/SimpleEgg
Author: UNKNOWN
Author-email: UNKNOWN
License: MIT
Platform: UNKNOWN
